MANIFEST.in
README.rst
setup.cfg
setup.py
cli/BaseController.py
cli/Mcg.py
cli/__init__.py
cli/init.py
cli/__pycache__/BaseController.cpython-34.pyc
cli/__pycache__/Mcg.cpython-34.pyc
cli/__pycache__/__init__.cpython-34.pyc
cli/__pycache__/init.cpython-34.pyc
core/Generator.py
core/GeneratorFactory.py
core/Manager.py
core/MethodsGenerator.py
core/MethodsTestsGenerator.py
core/ModelGenerator.py
core/ModelTestsGenerator.py
core/ProjectGenerator.py
core/PublicationGenerator.py
core/PublicationTestsGenerator.py
core/TestsGenerator.py
core/__init__.py
core/__pycache__/Generator.cpython-34.pyc
core/__pycache__/GeneratorFactory.cpython-34.pyc
core/__pycache__/Manager.cpython-34.pyc
core/__pycache__/MethodsGenerator.cpython-34.pyc
core/__pycache__/MethodsTestsGenerator.cpython-34.pyc
core/__pycache__/ModelGenerator.cpython-34.pyc
core/__pycache__/ModelTestsGenerator.cpython-34.pyc
core/__pycache__/ProjectGenerator.cpython-34.pyc
core/__pycache__/PublicationGenerator.cpython-34.pyc
core/__pycache__/PublicationTestsGenerator.cpython-34.pyc
core/__pycache__/TestsGenerator.cpython-34.pyc
core/__pycache__/__init__.cpython-34.pyc
core/db/MongoDB.py
core/db/Singleton.py
core/db/__init__.py
core/db/__pycache__/MongoDB.cpython-34.pyc
core/db/__pycache__/Singleton.cpython-34.pyc
core/db/__pycache__/__init__.cpython-34.pyc
mcg/__init__.py
mcg/main.py
mcg.egg-info/PKG-INFO
mcg.egg-info/SOURCES.txt
mcg.egg-info/dependency_links.txt
mcg.egg-info/entry_points.txt
mcg.egg-info/requires.txt
mcg.egg-info/top_level.txt
mcg/__pycache__/__init__.cpython-34.pyc
mcg/__pycache__/main.cpython-34.pyc