Metadata-Version: 1.1
Name: mcg
Version: 0.0.7
Summary: Meteor Project and API generator
Home-page: https://github.com/BizarroSolutions/mcg
Author: Bizarro Solutions (João Marcos Bizarro)
Author-email: info@bizarro.solutions
License: GNU General Public License v3 (GPLv3)
Keywords: mcg productivity meteor development
Platform: UNKNOWN
Classifier: Development Status :: 3 - Alpha
Classifier: Intended Audience :: Developers
Classifier: Topic :: Software Development :: Build Tools
Classifier: License :: OSI Approved :: GNU General Public License v3 (GPLv3)
Classifier: Programming Language :: Python :: 3
Classifier: Programming Language :: Python :: 3.2
Classifier: Programming Language :: Python :: 3.3
Classifier: Programming Language :: Python :: 3.4
